README
setup.py
django_jqmobile.egg-info/PKG-INFO
django_jqmobile.egg-info/SOURCES.txt
django_jqmobile.egg-info/dependency_links.txt
django_jqmobile.egg-info/not-zip-safe
django_jqmobile.egg-info/requires.txt
django_jqmobile.egg-info/top_level.txt
docs/CONTRIBUTORS
docs/HISTORY
docs/LICENSE
jqmobile/__init__.py
jqmobile/admin.py
jqmobile/exceptions.py
jqmobile/models.py
jqmobile/resolvers.py
jqmobile/settings.py
jqmobile/urls.py
jqmobile/validators.py
jqmobile/views.py
jqmobile/templates/jqmobile/base.html
jqmobile/templates/jqmobile/page.html