Metadata-Version: 1.0
Name: django-jqmobile
Version: 0.1
Summary: A Django Application for creating JQuery Mobile websites
Home-page: http://library.tamu.edu
Author: Benjamin Liles
Author-email: benliles@library.tamu.edu
License: Apache License 2.0
Keywords: django jquerymobile
Platform: UNKNOWN
Classifier: Framework :: Django
Classifier: Programming Language :: Python
Classifier: Intended Audience :: Developers
Classifier: License :: OSI Approved :: Apache Software License
Classifier: Topic :: Software Development :: Libraries :: Python Modules
Classifier: Development Status :: 3 - Alpha
